{
"WYU-WARRIOR_POWER.description": "你的攻击伤害会随当前生命降低而线性提高。满血时为100%，生命为0时为200%。",
"WYU-WARRIOR_POWER.smartDescription": "你的攻击伤害会随当前生命降低而线性提高。满血时为100%，生命为0时为200%。",
"WYU-WARRIOR_POWER.flavor": "[red]这个力量的细节将在未来揭晓……[/red]",
"WYU-WARRIOR_POWER.title": "武者力量",
"WYU-TORNADO_POWER.description": "下一回合清除所有层数,并对目标造成等同于层数的伤害。",
"WYU-TORNADO_POWER.smartDescription": "在{_turnsUntilTrigger}回合后(敌人行动{round}次后)清除所有层数,并对目标造成等同于层数的伤害。",
"WYU-TORNADO_POWER.flavor": "[red]这个力量的细节将在未来揭晓……[/red]",
"WYU-TORNADO_POWER.title": "龙卷风",
"WYU-FENG_YAN_POWER.description": "每回合开始无视护甲随机造成3点伤害3次。",
"WYU-FENG_YAN_POWER.smartDescription": "每回合开始对随机敌人造成伤害。",
"WYU-FENG_YAN_POWER.flavor": "[red]这个力量的细节将在未来揭晓……[/red]",
"WYU-FENG_YAN_POWER.title": "封烟行刑场",
"WYU-SIYE_BITE_POWER.description": "其余狼咬对该目标伤害增加,每层增加1点伤害。",
"WYU-SIYE_BITE_POWER.smartDescription": "其余狼咬对该目标伤害增加，每层增加1点伤害。",
"WYU-SIYE_BITE_POWER.flavor": "[red]这个力量的细节将在未来揭晓……[/red]",
"WYU-SIYE_BITE_POWER.title": "狼咬",
"WYU-RU_DONG_POWER.description": "该回合不会再受到任何伤害。",
"WYU-RU_DONG_POWER.smartDescription": "该回合不会再受到任何伤害。",
"WYU-RU_DONG_POWER.flavor": "[red]这个力量的细节将在未来揭晓……[/red]",
"WYU-RU_DONG_POWER.title": "蠕动",
"WYU-STEAL_DEFENCE_POWER.description": "下次攻击获得造成伤害的一半格挡。",
"WYU-STEAL_DEFENCE_POWER.smartDescription": "下次攻击获得造成伤害的一半格挡。",
"WYU-STEAL_DEFENCE_POWER.flavor": "[red]这个力量的细节将在未来揭晓……[/red]",
"WYU-STEAL_DEFENCE_POWER.title": "偷防",
"WYU-ARMOR_POWER.description": "下回合开始获得与层数相等的护甲",
"WYU-ARMOR_POWER.smartDescription": "下回合开始获得与层数相等的护甲",
"WYU-ARMOR_POWER.flavor": "[red]这个力量的细节将在未来揭晓……[/red]",
"WYU-ARMOR_POWER.title": "提前起防"
}